daterangeparser/__init__.py
daterangeparser/parse_date_range.py
daterangeparser/test.py
DateRangeParser-1.3.2.dist-info/COPYING
DateRangeParser-1.3.2.dist-info/COPYING.LESSER
DateRangeParser-1.3.2.dist-info/METADATA
DateRangeParser-1.3.2.dist-info/WHEEL
DateRangeParser-1.3.2.dist-info/top_level.txt
DateRangeParser-1.3.2.dist-info/RECORD
