Metadata-Version: 2.1
Name: DateRangeParser
Version: 1.3.2
Summary: Module to parse human-style date ranges (eg. 15th-19th March 2011) to datetimes
Home-page: https://github.com/robintw/daterangeparser
Author: Robin Wilson
Author-email: robin@rtwilson.com
License: LGPL
Platform: UNKNOWN
Classifier: Development Status :: 5 - Production/Stable
Classifier: Intended Audience :: Developers
Classifier: Topic :: Text Processing :: Linguistic
Classifier: Topic :: Software Development :: Libraries :: Python Modules
Classifier: License :: OSI Approved :: GNU Lesser General Public License v2 (LGPLv2)
Classifier: Programming Language :: Python
Classifier: Programming Language :: Python :: 3
Classifier: Programming Language :: Python :: 2
Requires-Dist: pyparsing
